schema_evolve.py
schema_evolve-0.4.0.dist-info/LICENSE
schema_evolve-0.4.0.dist-info/METADATA
schema_evolve-0.4.0.dist-info/WHEEL
schema_evolve-0.4.0.dist-info/top_level.txt
schema_evolve-0.4.0.dist-info/RECORD
