Metadata-Version: 2.1
Name: schema-evolve
Version: 0.4.0
Summary: A schema diff tool.
Author-email: Derek Anderson <public@kered.org>
Project-URL: Homepage, https://github.com/keredson/schema-evolve
Project-URL: Issues, https://github.com/keredson/schema-evolve/issues
Classifier: Programming Language :: Python :: 3
Classifier: License :: OSI Approved :: GNU General Public License v3 (GPLv3)
Classifier: Operating System :: OS Independent
Requires-Python: >=3.8
License-File: LICENSE
Requires-Dist: python-magic
Requires-Dist: sqlparse
Requires-Dist: darp
